<?xml version="1.0" encoding="utf-8"?>
<savedqueries xmlns:xsi="http://www.w3.org/2001/XMLSchema-instance">
  <savedquery>
    <IsCustomizable>1</IsCustomizable>
    <CanBeDeleted>0</CanBeDeleted>
    <isquickfindquery>0</isquickfindquery>
    <isprivate>0</isprivate>
    <isdefault>1</isdefault>
    <savedqueryid>{23cde4f4-c8d1-4821-b0d6-1ee52204a229}</savedqueryid>
    <layoutxml>
      <grid name="resultset" jump="ovs_name" select="1" icon="1" preview="1">
        <row name="result" id="ovs_incidenterapid">
          <cell name="ovs_name" width="300" />
          <cell name="ovs_incident_report_id" width="150" />
          <cell name="createdon" width="125" />
        </row>
      </grid>
    </layoutxml>
    <querytype>0</querytype>
    <fetchxml>
      <fetch version="1.0" mapping="logical">
        <entity name="ovs_incidenterap">
          <attribute name="ovs_incidenterapid" />
          <attribute name="ovs_name" />
          <attribute name="createdon" />
          <order attribute="ovs_name" descending="false" />
          <filter type="and">
            <condition attribute="statecode" operator="eq" value="0" />
          </filter>
          <attribute name="ovs_incident_report_id" />
        </entity>
      </fetch>
    </fetchxml>
    <IntroducedVersion>1.0</IntroducedVersion>
    <LocalizedNames>
      <LocalizedName description="Active Incident ERAPS" languagecode="1033" />
    </LocalizedNames>
  </savedquery>
</savedqueries>